mousepad/.DS_Store
mousepad/__main__.py
mousepad/webbuild/.DS_Store
mousepad/webbuild/flutter_assets/.DS_Store
mousepad/webbuild/flutter_assets/AssetManifest.bin
mousepad/webbuild/flutter_assets/AssetManifest.bin.json
mousepad/webbuild/flutter_assets/AssetManifest.json
mousepad/webbuild/flutter_assets/FontManifest.json
mousepad/webbuild/flutter_assets/NOTICES
mousepad/webbuild/flutter_assets/assets/images/AirDrop.svg
mousepad/webbuild/flutter_assets/assets/images/display.svg
mousepad/webbuild/flutter_assets/assets/images/gaming.svg
mousepad/webbuild/flutter_assets/assets/images/keyboard.svg
mousepad/webbuild/flutter_assets/fonts/MaterialIcons-Regular.otf
mousepad/webbuild/flutter_assets/packages/.DS_Store
mousepad/webbuild/flutter_assets/packages/cupertino_icons/assets/CupertinoIcons.ttf
mousepad/webbuild/flutter_assets/shaders/ink_sparkle.frag
mousepad/webbuild/web/.DS_Store
mousepad/webbuild/web/.last_build_id
mousepad/webbuild/web/favicon.png
mousepad/webbuild/web/flutter.js
mousepad/webbuild/web/flutter_service_worker.js
mousepad/webbuild/web/index.html
mousepad/webbuild/web/main.dart.js
mousepad/webbuild/web/manifest.json
mousepad/webbuild/web/version.json
mousepad/webbuild/web/assets/.DS_Store
mousepad/webbuild/web/assets/AssetManifest.bin
mousepad/webbuild/web/assets/AssetManifest.bin.json
mousepad/webbuild/web/assets/AssetManifest.json
mousepad/webbuild/web/assets/FontManifest.json
mousepad/webbuild/web/assets/NOTICES
mousepad/webbuild/web/assets/assets/images/AirDrop.svg
mousepad/webbuild/web/assets/assets/images/display.svg
mousepad/webbuild/web/assets/assets/images/gaming.svg
mousepad/webbuild/web/assets/assets/images/keyboard.svg
mousepad/webbuild/web/assets/fonts/MaterialIcons-Regular.otf
mousepad/webbuild/web/assets/packages/cupertino_icons/assets/CupertinoIcons.ttf
mousepad/webbuild/web/assets/shaders/ink_sparkle.frag
mousepad/webbuild/web/canvaskit/canvaskit.js
mousepad/webbuild/web/canvaskit/canvaskit.js.symbols
mousepad-0.1.3.dist-info/LICENSE
mousepad-0.1.3.dist-info/METADATA
mousepad-0.1.3.dist-info/WHEEL
mousepad-0.1.3.dist-info/top_level.txt
mousepad-0.1.3.dist-info/RECORD
